README.md
setup.py
pyyutil/__init__.py
pyyutil/pyyfile.py
pyyutil/pyyhttp.py
pyyutil.egg-info/PKG-INFO
pyyutil.egg-info/SOURCES.txt
pyyutil.egg-info/dependency_links.txt
pyyutil.egg-info/top_level.txt