Metadata-Version: 2.4
Name: pyyutil
Version: 0.0.1
Summary: pyyutil是py高效工具
Author: yanyue
Author-email: 
Keywords: utils,python,pyyutil,python utils,windows,mac,linux
Classifier: Development Status :: 1 - Planning
Classifier: Intended Audience :: Developers
Classifier: Programming Language :: Python :: 3
Classifier: Operating System :: Unix
Classifier: Operating System :: MacOS :: MacOS X
Classifier: Operating System :: Microsoft :: Windows
Dynamic: author
Dynamic: classifier
Dynamic: description
Dynamic: description-content-type
Dynamic: keywords
Dynamic: summary
